COPYING
README.md
setup.py
mvapi/__init__.py
mvapi/version.py
mvapi.egg-info/PKG-INFO
mvapi.egg-info/SOURCES.txt
mvapi.egg-info/dependency_links.txt
mvapi.egg-info/entry_points.txt
mvapi.egg-info/requires.txt
mvapi.egg-info/top_level.txt
mvapi/cli/__init__.py
mvapi/cli/mvapi/__init__.py
mvapi/cli/mvapi/init_project.py
mvapi/cli/project/__init__.py
mvapi/cli/project/run_temp_script.py
mvapi/cli/project/migration/__init__.py
mvapi/cli/project/migration/downgrade.py
mvapi/cli/project/migration/init.py
mvapi/cli/project/migration/revision.py
mvapi/cli/project/migration/upgrade.py
mvapi/cli/project/migration/utils.py
mvapi/cli/project/user/__init__.py
mvapi/cli/project/user/create_user.py
mvapi/cli/project/user/update_user.py
mvapi/cli/project/web/__init__.py
mvapi/cli/project/web/run.py
mvapi/libs/__init__.py
mvapi/libs/database.py
mvapi/libs/error.py
mvapi/libs/exceptions.py
mvapi/libs/logger.py
mvapi/libs/misc.py
mvapi/libs/run.py
mvapi/models/__init__.py
mvapi/settings/__init__.py
mvapi/settings/default_settings.py
mvapi/templates/error.tmpl
mvapi/web/__init__.py
mvapi/web/urls.py
mvapi/web/libs/__init__.py
mvapi/web/libs/appfactory.py
mvapi/web/libs/decorators.py
mvapi/web/libs/exceptions.py
mvapi/web/libs/extensions.py
mvapi/web/libs/jsonwebtoken.py
mvapi/web/libs/logger.py
mvapi/web/libs/misc.py
mvapi/web/models/__init__.py
mvapi/web/models/session.py
mvapi/web/models/user.py
mvapi/web/serializers/__init__.py
mvapi/web/serializers/base.py
mvapi/web/serializers/items.py
mvapi/web/serializers/session.py
mvapi/web/serializers/user.py
mvapi/web/views/__init__.py
mvapi/web/views/api.py
mvapi/web/views/base.py
mvapi/web/views/sessions.py
mvapi/web/views/users.py