Metadata-Version: 1.2
Name: mvapi
Version: 0.1.5
Summary: Skeleton for a JSON API project
Home-page: https://git.vetoshkin.dev/mvapi/
Author: Mikhail Vetoshkin
Author-email: mikhail@vetoshkin.dev
License: GNU General Public License v3 (GPLv3)
Platform: UNKNOWN
Requires-Python: >=3.9
